tdry/__init__.py
tdry/__main__.py
tdry/cli.py
tdry/colors.py
tdry/configuration.py
tdry/exceptions.py
tdry/formatters.py
tdry/interactive.py
tdry/model.py
tdry/version.py
tdry/widgets.py
tdry-1.0.2.dist-info/AUTHORS.rst
tdry-1.0.2.dist-info/LICENCE
tdry-1.0.2.dist-info/METADATA
tdry-1.0.2.dist-info/WHEEL
tdry-1.0.2.dist-info/entry_points.txt
tdry-1.0.2.dist-info/top_level.txt
tdry-1.0.2.dist-info/RECORD
