Metadata-Version: 2.1
Name: tdry
Version: 1.0.2
Summary: For people who like to plan their life, easy to use icalendar-based todo manager. Forked from todoman.
Author-email: rooyca <rooyca@gmail.com>
License: ISC
Project-URL: homepage, https://github.com/rooyca/tdry
Project-URL: changelog, https://github.com/rooyca/tdry/blob/main/CHANGELOG.rst
Project-URL: issues, https://github.com/rooyca/tdry/issues
Classifier: Development Status :: 5 - Production/Stable
Classifier: Environment :: Console
Classifier: Environment :: Console :: Curses
Classifier: License :: OSI Approved :: ISC License (ISCL)
Classifier: Operating System :: POSIX
Classifier: Programming Language :: Python :: 3.8
Classifier: Programming Language :: Python :: 3.9
Classifier: Programming Language :: Python :: 3.10
Classifier: Programming Language :: Python :: 3.11
Classifier: Programming Language :: Python :: Implementation :: PyPy
Classifier: Topic :: Office/Business :: Scheduling
Classifier: Topic :: Utilities
Requires-Python: >=3.8
License-File: LICENCE
License-File: AUTHORS.rst
Requires-Dist: click <9.0,>=7.1
Requires-Dist: click-log >=0.2.1
Requires-Dist: humanize
Requires-Dist: icalendar >=4.0.3
Requires-Dist: parsedatetime
Requires-Dist: python-dateutil
Requires-Dist: pyxdg
Requires-Dist: urwid
Requires-Dist: tinydb >=4.8.0
Provides-Extra: repl
Requires-Dist: click-repl >=0.1.6 ; extra == 'repl'
